rag_webquery/__init__.py
rag_webquery/rag_webquery.py
rag_webquery-0.1.1.dist-info/LICENSE
rag_webquery-0.1.1.dist-info/METADATA
rag_webquery-0.1.1.dist-info/WHEEL
rag_webquery-0.1.1.dist-info/entry_points.txt
rag_webquery-0.1.1.dist-info/RECORD
