Metadata-Version: 2.1
Name: rag_webquery
Version: 0.1.1
Summary: A command line utility to query websites using a local LLM
Home-page: https://github.com/robert-mcdermott/rag_webquery
License: Apache-2.0
Keywords: llm
Author: Robert McDermott
Author-email: robert.c.mcdermott@gmail.com
Requires-Python: >=3.9,<4.0
Classifier: License :: OSI Approved :: Apache Software License
Classifier: Programming Language :: Python :: 3
Classifier: Programming Language :: Python :: 3.9
Classifier: Programming Language :: Python :: 3.10
Classifier: Programming Language :: Python :: 3.11
Requires-Dist: bs4 (>=0.0.1,<0.0.2)
Requires-Dist: chromadb (==0.4.15)
Requires-Dist: gpt4all (>=2.0.2,<3.0.0)
Requires-Dist: langchain (>=0.1.0,<0.2.0)
Requires-Dist: langchain-community (>=0.0.9,<0.0.10)
Requires-Dist: requests (>=2.31.0,<3.0.0)
Project-URL: Repository, https://github.com/robert-mcdermott/rag_webquery
